pixelbuf_pi_animation/__init__.py
pixelbuf_pi_animation/data.py
pixelbuf_pi_animation/parser.py
pixelbuf_pi_animation/player.py
pixelbuf_pi_animation-0.0.2.dist-info/LICENSE
pixelbuf_pi_animation-0.0.2.dist-info/METADATA
pixelbuf_pi_animation-0.0.2.dist-info/WHEEL
pixelbuf_pi_animation-0.0.2.dist-info/top_level.txt
pixelbuf_pi_animation-0.0.2.dist-info/RECORD
