Metadata-Version: 2.1
Name: pixelbuf-pi-animation
Version: 0.0.2
Summary: A package to render Adafruit LED products using the Raspberry Pi
Home-page: https://github.com/Sectional-Art/pixelbuf-pi-animation
Author: Brian Stempin
Author-email: brian.stempin@gmail.com
License: UNKNOWN
Project-URL: Documentation, https://pixelbuf-pi-animation.readthedocs.io/en/latest/
Platform: UNKNOWN
Classifier: Development Status :: 3 - Alpha
Classifier: Programming Language :: Python :: 3
Classifier: License :: OSI Approved :: MIT License
Classifier: Operating System :: OS Independent
Classifier: Intended Audience :: Developers
Classifier: Topic :: Software Development :: Libraries
Classifier: Topic :: System :: Hardware
Requires-Python: >=3.6
License-File: LICENSE
Requires-Dist: adafruit-circuitpython-pixelbuf (>="1.1.1")
Requires-Dist: dacite (>="1.6.0")
Requires-Dist: msgpack (>="1.0.1")
